<?xml version="1.0" encoding="UTF-8"?>
<!DOCTYPE markables SYSTEM "markables.dtd">
<markables xmlns="www.eml.org/NameSpaces/sentence">
<markable id="markable_1" span="word_1..word_10" mmax_level="sentence"/>
<markable id="markable_3" span="word_11..word_18" mmax_level="sentence"/>
<markable id="markable_5" span="word_19..word_20" mmax_level="sentence"/>
<markable id="markable_7" span="word_21..word_43" mmax_level="sentence"/>
<markable id="markable_9" span="word_44..word_56" mmax_level="sentence"/>
<markable id="markable_11" span="word_57..word_70" mmax_level="sentence"/>
<markable id="markable_13" span="word_71..word_105" mmax_level="sentence"/>
<markable id="markable_15" span="word_106..word_143" mmax_level="sentence"/>
</markables>
